{
  "kind": "assets",
  "code": "AEBI",
  "asset_id": 565,
  "points": [
    {
      "dt": "2025-07-01",
      "value": 83.0888241,
      "open_p": 83.0888241,
      "high_p": 83.0888241,
      "low_p": 83.0888241
    },
    {
      "dt": "2025-07-02",
      "value": 11.15701481,
      "open_p": 32.872278,
      "high_p": 32.93205485,
      "low_p": 10.07923521
    },
    {
      "dt": "2025-07-03",
      "value": 13.58201893,
      "open_p": 14.07101153,
      "high_p": 14.97914064,
      "low_p": 11.78571958
    },
    {
      "dt": "2025-07-07",
      "value": 12.10506169,
      "open_p": 12.39446547,
      "high_p": 13.37245067,
      "low_p": 11.40650083
    },
    {
      "dt": "2025-07-08",
      "value": 11.59611021,
      "open_p": 12.21483554,
      "high_p": 12.21483554,
      "low_p": 11.03726152
    },
    {
      "dt": "2025-07-09",
      "value": 11.79569903,
      "open_p": 11.34662419,
      "high_p": 11.94539064,
      "low_p": 10.79755536
    },
    {
      "dt": "2025-07-10",
      "value": 11.45639804,
      "open_p": 11.52625412,
      "high_p": 11.84559623,
      "low_p": 11.37656251
    },
    {
      "dt": "2025-07-11",
      "value": 11.04724097,
      "open_p": 11.28674754,
      "high_p": 11.60608965,
      "low_p": 10.99734376
    },
    {
      "dt": "2025-07-14",
      "value": 10.28880346,
      "open_p": 10.97738488,
      "high_p": 10.99734376,
      "low_p": 10.08921465
    },
    {
      "dt": "2025-07-15",
      "value": 10.09919409,
      "open_p": 10.29878291,
      "high_p": 10.39857731,
      "low_p": 10.029338
    },
    {
      "dt": "2025-07-16",
      "value": 10.18900906,
      "open_p": 10.03931744,
      "high_p": 10.72789886,
      "low_p": 9.9794408
    },
    {
      "dt": "2025-07-17",
      "value": 10.21894738,
      "open_p": 9.99939968,
      "high_p": 10.47831305,
      "low_p": 9.87964639
    },
    {
      "dt": "2025-07-18",
      "value": 9.89960527,
      "open_p": 10.00937912,
      "high_p": 10.31874179,
      "low_p": 9.74003402
    },
    {
      "dt": "2025-07-21",
      "value": 9.24096218,
      "open_p": 9.90958471,
      "high_p": 10.20896794,
      "low_p": 8.89168175
    },
    {
      "dt": "2025-07-22",
      "value": 9.34075659,
      "open_p": 9.38067435,
      "high_p": 9.95948192,
      "low_p": 8.98149672
    },
    {
      "dt": "2025-07-23",
      "value": 9.53036596,
      "open_p": 9.31081827,
      "high_p": 9.87964639,
      "low_p": 9.20104442
    },
    {
      "dt": "2025-07-24",
      "value": 9.86966695,
      "open_p": 9.65011925,
      "high_p": 10.16895038,
      "low_p": 9.4904482
    },
    {
      "dt": "2025-07-25",
      "value": 9.7598931,
      "open_p": 9.9794408,
      "high_p": 9.9794408,
      "low_p": 9.4654996
    },
    {
      "dt": "2025-07-28",
      "value": 9.80979031,
      "open_p": 9.5403454,
      "high_p": 9.95948192,
      "low_p": 9.4904482
    },
    {
      "dt": "2025-07-29",
      "value": 10.01935856,
      "open_p": 9.76987254,
      "high_p": 10.13901206,
      "low_p": 9.7011142
    },
    {
      "dt": "2025-07-30",
      "value": 10.15907073,
      "open_p": 10.09919409,
      "high_p": 10.72789886,
      "low_p": 9.92455388
    },
    {
      "dt": "2025-07-31",
      "value": 10.27882402,
      "open_p": 10.08921465,
      "high_p": 10.43849508,
      "low_p": 9.86966695
    },
    {
      "dt": "2025-08-01",
      "value": 9.70001646,
      "open_p": 10.17902962,
      "high_p": 10.27882402,
      "low_p": 9.70001646
    },
    {
      "dt": "2025-08-04",
      "value": 10.97738488,
      "open_p": 9.9794408,
      "high_p": 11.10711761,
      "low_p": 9.95948192
    },
    {
      "dt": "2025-08-05",
      "value": 10.79775495,
      "open_p": 11.09713817,
      "high_p": 11.16420001,
      "low_p": 10.30876235
    },
    {
      "dt": "2025-08-06",
      "value": 10.4684334,
      "open_p": 10.82769327,
      "high_p": 10.92748768,
      "low_p": 10.39857731
    },
    {
      "dt": "2025-08-07",
      "value": 10.36863899,
      "open_p": 10.32872123,
      "high_p": 10.70793998,
      "low_p": 10.26385486
    },
    {
      "dt": "2025-08-08",
      "value": 11.09713817,
      "open_p": 10.50835116,
      "high_p": 11.68592518,
      "low_p": 10.37861843
    },
    {
      "dt": "2025-08-11",
      "value": 11.09713817,
      "open_p": 11.1769737,
      "high_p": 11.2767681,
      "low_p": 10.83767271
    },
    {
      "dt": "2025-08-12",
      "value": 11.46637748,
      "open_p": 11.07717929,
      "high_p": 11.68592518,
      "low_p": 10.94744656
    },
    {
      "dt": "2025-08-13",
      "value": 12.16493834,
      "open_p": 11.62604853,
      "high_p": 12.17491778,
      "low_p": 11.4464186
    },
    {
      "dt": "2025-08-14",
      "value": 12.12502057,
      "open_p": 10.92748768,
      "high_p": 12.41442436,
      "low_p": 10.92748768
    },
    {
      "dt": "2025-08-15",
      "value": 11.77574014,
      "open_p": 12.10506169,
      "high_p": 12.34955799,
      "low_p": 11.74580182
    },
    {
      "dt": "2025-08-18",
      "value": 11.87553455,
      "open_p": 11.83561679,
      "high_p": 12.22481498,
      "low_p": 11.47635692
    },
    {
      "dt": "2025-08-19",
      "value": 11.70588406,
      "open_p": 12.05516449,
      "high_p": 12.29467107,
      "low_p": 11.61606909
    },
    {
      "dt": "2025-08-20",
      "value": 11.45639804,
      "open_p": 11.97532896,
      "high_p": 12.14288377,
      "low_p": 11.2268709
    },
    {
      "dt": "2025-08-21",
      "value": 11.63602797,
      "open_p": 11.53623356,
      "high_p": 12.01524672,
      "low_p": 11.43643916
    },
    {
      "dt": "2025-08-22",
      "value": 12.21483554,
      "open_p": 11.63602797,
      "high_p": 12.27471218,
      "low_p": 11.63602797
    },
    {
      "dt": "2025-08-25",
      "value": 11.64600741,
      "open_p": 12.39446547,
      "high_p": 12.39446547,
      "low_p": 11.37656251
    },
    {
      "dt": "2025-08-26",
      "value": 11.99528784,
      "open_p": 11.74580182,
      "high_p": 12.26473274,
      "low_p": 11.6659663
    },
    {
      "dt": "2025-08-27",
      "value": 11.80567847,
      "open_p": 11.95537008,
      "high_p": 12.16394039,
      "low_p": 11.59611021
    },
    {
      "dt": "2025-08-28",
      "value": 12.13500001,
      "open_p": 11.81565791,
      "high_p": 12.4244038,
      "low_p": 11.71476576
    },
    {
      "dt": "2025-08-29",
      "value": 12.29,
      "open_p": 12.12,
      "high_p": 12.36,
      "low_p": 11.72
    },
    {
      "dt": "2025-09-02",
      "value": 12.0,
      "open_p": 12.2,
      "high_p": 12.79,
      "low_p": 11.92
    },
    {
      "dt": "2025-09-03",
      "value": 11.49,
      "open_p": 11.95,
      "high_p": 12.05,
      "low_p": 10.89
    },
    {
      "dt": "2025-09-04",
      "value": 11.35,
      "open_p": 11.55,
      "high_p": 11.565,
      "low_p": 11.09
    },
    {
      "dt": "2025-09-05",
      "value": 11.71,
      "open_p": 11.35,
      "high_p": 11.775,
      "low_p": 11.1
    },
    {
      "dt": "2025-09-08",
      "value": 11.76,
      "open_p": 11.83,
      "high_p": 12.105,
      "low_p": 11.6
    },
    {
      "dt": "2025-09-09",
      "value": 11.77,
      "open_p": 11.76,
      "high_p": 11.86,
      "low_p": 11.59
    },
    {
      "dt": "2025-09-10",
      "value": 11.82,
      "open_p": 11.61,
      "high_p": 12.03,
      "low_p": 11.61
    },
    {
      "dt": "2025-09-11",
      "value": 12.49,
      "open_p": 11.92,
      "high_p": 12.5,
      "low_p": 11.7011
    },
    {
      "dt": "2025-09-12",
      "value": 12.41,
      "open_p": 12.47,
      "high_p": 12.55,
      "low_p": 12.19
    },
    {
      "dt": "2025-09-15",
      "value": 12.55,
      "open_p": 12.5,
      "high_p": 12.66,
      "low_p": 12.3
    },
    {
      "dt": "2025-09-16",
      "value": 12.52,
      "open_p": 12.55,
      "high_p": 12.63,
      "low_p": 12.26
    },
    {
      "dt": "2025-09-17",
      "value": 12.18,
      "open_p": 12.68,
      "high_p": 13.0,
      "low_p": 12.0
    },
    {
      "dt": "2025-09-18",
      "value": 12.69,
      "open_p": 12.27,
      "high_p": 12.73,
      "low_p": 12.17
    },
    {
      "dt": "2025-09-19",
      "value": 12.49,
      "open_p": 12.5,
      "high_p": 12.72,
      "low_p": 12.395
    },
    {
      "dt": "2025-09-22",
      "value": 13.58,
      "open_p": 12.52,
      "high_p": 13.6,
      "low_p": 12.08
    },
    {
      "dt": "2025-09-23",
      "value": 12.85,
      "open_p": 13.42,
      "high_p": 13.85,
      "low_p": 12.72
    },
    {
      "dt": "2025-09-24",
      "value": 12.59,
      "open_p": 12.97,
      "high_p": 13.14,
      "low_p": 12.52
    },
    {
      "dt": "2025-09-25",
      "value": 12.25,
      "open_p": 12.52,
      "high_p": 12.53,
      "low_p": 12.19
    },
    {
      "dt": "2025-09-26",
      "value": 12.71,
      "open_p": 12.3,
      "high_p": 12.75,
      "low_p": 12.2
    },
    {
      "dt": "2025-09-29",
      "value": 12.9,
      "open_p": 12.74,
      "high_p": 12.92,
      "low_p": 12.29
    },
    {
      "dt": "2025-09-30",
      "value": 12.47,
      "open_p": 12.77,
      "high_p": 12.92,
      "low_p": 12.22
    },
    {
      "dt": "2025-10-01",
      "value": 12.49,
      "open_p": 12.4,
      "high_p": 12.57,
      "low_p": 12.25
    },
    {
      "dt": "2025-10-02",
      "value": 12.25,
      "open_p": 12.59,
      "high_p": 12.625,
      "low_p": 12.17
    },
    {
      "dt": "2025-10-03",
      "value": 12.4,
      "open_p": 12.24,
      "high_p": 12.48,
      "low_p": 12.09
    },
    {
      "dt": "2025-10-06",
      "value": 12.25,
      "open_p": 12.45,
      "high_p": 12.69,
      "low_p": 12.12
    },
    {
      "dt": "2025-10-07",
      "value": 12.12,
      "open_p": 12.22,
      "high_p": 12.355,
      "low_p": 12.025
    },
    {
      "dt": "2025-10-08",
      "value": 11.83,
      "open_p": 12.11,
      "high_p": 12.2,
      "low_p": 11.735
    },
    {
      "dt": "2025-10-09",
      "value": 11.99,
      "open_p": 11.77,
      "high_p": 11.99,
      "low_p": 11.54
    },
    {
      "dt": "2025-10-10",
      "value": 11.13,
      "open_p": 11.95,
      "high_p": 12.09,
      "low_p": 11.12
    }
  ]
}