{
  "kind": "indicators",
  "code": "EXUSAL",
  "id": 49,
  "points": [
    {
      "dt": "1971-01-01",
      "value": 1.1181
    },
    {
      "dt": "1971-02-01",
      "value": 1.1238
    },
    {
      "dt": "1971-03-01",
      "value": 1.1243
    },
    {
      "dt": "1971-04-01",
      "value": 1.1238
    },
    {
      "dt": "1971-05-01",
      "value": 1.1243
    },
    {
      "dt": "1971-06-01",
      "value": 1.1243
    },
    {
      "dt": "1971-07-01",
      "value": 1.1241
    },
    {
      "dt": "1971-08-01",
      "value": 1.1316
    },
    {
      "dt": "1971-09-01",
      "value": 1.1478
    },
    {
      "dt": "1971-10-01",
      "value": 1.1577
    },
    {
      "dt": "1971-11-01",
      "value": 1.1589
    },
    {
      "dt": "1971-12-01",
      "value": 1.1748
    },
    {
      "dt": "1972-01-01",
      "value": 1.191
    },
    {
      "dt": "1972-02-01",
      "value": 1.191
    },
    {
      "dt": "1972-03-01",
      "value": 1.191
    },
    {
      "dt": "1972-04-01",
      "value": 1.191
    },
    {
      "dt": "1972-05-01",
      "value": 1.191
    },
    {
      "dt": "1972-06-01",
      "value": 1.191
    },
    {
      "dt": "1972-07-01",
      "value": 1.191
    },
    {
      "dt": "1972-08-01",
      "value": 1.1911
    },
    {
      "dt": "1972-09-01",
      "value": 1.191
    },
    {
      "dt": "1972-10-01",
      "value": 1.1907
    },
    {
      "dt": "1972-11-01",
      "value": 1.1909
    },
    {
      "dt": "1972-12-01",
      "value": 1.2074
    },
    {
      "dt": "1973-01-01",
      "value": 1.2716
    },
    {
      "dt": "1973-02-01",
      "value": 1.3546
    },
    {
      "dt": "1973-03-01",
      "value": 1.4129
    },
    {
      "dt": "1973-04-01",
      "value": 1.415
    },
    {
      "dt": "1973-05-01",
      "value": 1.415
    },
    {
      "dt": "1973-06-01",
      "value": 1.4158
    },
    {
      "dt": "1973-07-01",
      "value": 1.4178
    },
    {
      "dt": "1973-08-01",
      "value": 1.4148
    },
    {
      "dt": "1973-09-01",
      "value": 1.4683
    },
    {
      "dt": "1973-10-01",
      "value": 1.4823
    },
    {
      "dt": "1973-11-01",
      "value": 1.4822
    },
    {
      "dt": "1973-12-01",
      "value": 1.4833
    },
    {
      "dt": "1974-01-01",
      "value": 1.4823
    },
    {
      "dt": "1974-02-01",
      "value": 1.485
    },
    {
      "dt": "1974-03-01",
      "value": 1.4855
    },
    {
      "dt": "1974-04-01",
      "value": 1.4841
    },
    {
      "dt": "1974-05-01",
      "value": 1.4844
    },
    {
      "dt": "1974-06-01",
      "value": 1.4834
    },
    {
      "dt": "1974-07-01",
      "value": 1.4799
    },
    {
      "dt": "1974-08-01",
      "value": 1.4824
    },
    {
      "dt": "1974-09-01",
      "value": 1.4487
    },
    {
      "dt": "1974-10-01",
      "value": 1.3093
    },
    {
      "dt": "1974-11-01",
      "value": 1.311
    },
    {
      "dt": "1974-12-01",
      "value": 1.3172
    },
    {
      "dt": "1975-01-01",
      "value": 1.3295
    },
    {
      "dt": "1975-02-01",
      "value": 1.348
    },
    {
      "dt": "1975-03-01",
      "value": 1.3585
    },
    {
      "dt": "1975-04-01",
      "value": 1.3416
    },
    {
      "dt": "1975-05-01",
      "value": 1.3404
    },
    {
      "dt": "1975-06-01",
      "value": 1.3355
    },
    {
      "dt": "1975-07-01",
      "value": 1.3095
    },
    {
      "dt": "1975-08-01",
      "value": 1.2815
    },
    {
      "dt": "1975-09-01",
      "value": 1.2687
    },
    {
      "dt": "1975-10-01",
      "value": 1.2626
    },
    {
      "dt": "1975-11-01",
      "value": 1.2626
    },
    {
      "dt": "1975-12-01",
      "value": 1.2538
    },
    {
      "dt": "1976-01-01",
      "value": 1.2565
    },
    {
      "dt": "1976-02-01",
      "value": 1.2585
    },
    {
      "dt": "1976-03-01",
      "value": 1.2479
    },
    {
      "dt": "1976-04-01",
      "value": 1.2372
    },
    {
      "dt": "1976-05-01",
      "value": 1.2337
    },
    {
      "dt": "1976-06-01",
      "value": 1.2275
    },
    {
      "dt": "1976-07-01",
      "value": 1.2359
    },
    {
      "dt": "1976-08-01",
      "value": 1.2418
    },
    {
      "dt": "1976-09-01",
      "value": 1.2425
    },
    {
      "dt": "1976-10-01",
      "value": 1.234
    },
    {
      "dt": "1976-11-01",
      "value": 1.2066
    },
    {
      "dt": "1976-12-01",
      "value": 1.0529
    },
    {
      "dt": "1977-01-01",
      "value": 1.0853
    },
    {
      "dt": "1977-02-01",
      "value": 1.0904
    },
    {
      "dt": "1977-03-01",
      "value": 1.0994
    },
    {
      "dt": "1977-04-01",
      "value": 1.1053
    },
    {
      "dt": "1977-05-01",
      "value": 1.1031
    },
    {
      "dt": "1977-06-01",
      "value": 1.108
    },
    {
      "dt": "1977-07-01",
      "value": 1.122
    },
    {
      "dt": "1977-08-01",
      "value": 1.1047
    },
    {
      "dt": "1977-09-01",
      "value": 1.1037
    },
    {
      "dt": "1977-10-01",
      "value": 1.119
    },
    {
      "dt": "1977-11-01",
      "value": 1.127
    },
    {
      "dt": "1977-12-01",
      "value": 1.1336
    },
    {
      "dt": "1978-01-01",
      "value": 1.1382
    },
    {
      "dt": "1978-02-01",
      "value": 1.1356
    },
    {
      "dt": "1978-03-01",
      "value": 1.1383
    },
    {
      "dt": "1978-04-01",
      "value": 1.1397
    },
    {
      "dt": "1978-05-01",
      "value": 1.1276
    },
    {
      "dt": "1978-06-01",
      "value": 1.1383
    },
    {
      "dt": "1978-07-01",
      "value": 1.1494
    },
    {
      "dt": "1978-08-01",
      "value": 1.1541
    },
    {
      "dt": "1978-09-01",
      "value": 1.1529
    },
    {
      "dt": "1978-10-01",
      "value": 1.1687
    },
    {
      "dt": "1978-11-01",
      "value": 1.1453
    },
    {
      "dt": "1978-12-01",
      "value": 1.1415
    },
    {
      "dt": "1979-01-01",
      "value": 1.1404
    },
    {
      "dt": "1979-02-01",
      "value": 1.1312
    },
    {
      "dt": "1979-03-01",
      "value": 1.1215
    },
    {
      "dt": "1979-04-01",
      "value": 1.1085
    },
    {
      "dt": "1979-05-01",
      "value": 1.1057
    },
    {
      "dt": "1979-06-01",
      "value": 1.1111
    },
    {
      "dt": "1979-07-01",
      "value": 1.1283
    },
    {
      "dt": "1979-08-01",
      "value": 1.1283
    },
    {
      "dt": "1979-09-01",
      "value": 1.1263
    },
    {
      "dt": "1979-10-01",
      "value": 1.1131
    },
    {
      "dt": "1979-11-01",
      "value": 1.0934
    },
    {
      "dt": "1979-12-01",
      "value": 1.103
    },
    {
      "dt": "1980-01-01",
      "value": 1.1097
    },
    {
      "dt": "1980-02-01",
      "value": 1.1041
    },
    {
      "dt": "1980-03-01",
      "value": 1.0903
    },
    {
      "dt": "1980-04-01",
      "value": 1.091
    },
    {
      "dt": "1980-05-01",
      "value": 1.1302
    },
    {
      "dt": "1980-06-01",
      "value": 1.1529
    },
    {
      "dt": "1980-07-01",
      "value": 1.1585
    },
    {
      "dt": "1980-08-01",
      "value": 1.1577
    },
    {
      "dt": "1980-09-01",
      "value": 1.1704
    },
    {
      "dt": "1980-10-01",
      "value": 1.1743
    },
    {
      "dt": "1980-11-01",
      "value": 1.1675
    },
    {
      "dt": "1980-12-01",
      "value": 1.1686
    },
    {
      "dt": "1981-01-01",
      "value": 1.1819
    },
    {
      "dt": "1981-02-01",
      "value": 1.1626
    },
    {
      "dt": "1981-03-01",
      "value": 1.1629
    },
    {
      "dt": "1981-04-01",
      "value": 1.1532
    },
    {
      "dt": "1981-05-01",
      "value": 1.1406
    },
    {
      "dt": "1981-06-01",
      "value": 1.1407
    },
    {
      "dt": "1981-07-01",
      "value": 1.1427
    },
    {
      "dt": "1981-08-01",
      "value": 1.1399
    },
    {
      "dt": "1981-09-01",
      "value": 1.1486
    },
    {
      "dt": "1981-10-01",
      "value": 1.1432
    },
    {
      "dt": "1981-11-01",
      "value": 1.1455
    },
    {
      "dt": "1981-12-01",
      "value": 1.1339
    },
    {
      "dt": "1982-01-01",
      "value": 1.1141
    },
    {
      "dt": "1982-02-01",
      "value": 1.085
    },
    {
      "dt": "1982-03-01",
      "value": 1.0603
    },
    {
      "dt": "1982-04-01",
      "value": 1.0515
    },
    {
      "dt": "1982-05-01",
      "value": 1.0594
    },
    {
      "dt": "1982-06-01",
      "value": 1.0323
    },
    {
      "dt": "1982-07-01",
      "value": 1.0109
    },
    {
      "dt": "1982-08-01",
      "value": 0.9784
    },
    {
      "dt": "1982-09-01",
      "value": 0.9582
    },
    {
      "dt": "1982-10-01",
      "value": 0.9435
    },
    {
      "dt": "1982-11-01",
      "value": 0.9427
    },
    {
      "dt": "1982-12-01",
      "value": 0.9682
    },
    {
      "dt": "1983-01-01",
      "value": 0.9826
    },
    {
      "dt": "1983-02-01",
      "value": 0.9662
    },
    {
      "dt": "1983-03-01",
      "value": 0.8839
    },
    {
      "dt": "1983-04-01",
      "value": 0.8676
    },
    {
      "dt": "1983-05-01",
      "value": 0.8785
    },
    {
      "dt": "1983-06-01",
      "value": 0.8772
    },
    {
      "dt": "1983-07-01",
      "value": 0.8754
    },
    {
      "dt": "1983-08-01",
      "value": 0.8793
    },
    {
      "dt": "1983-09-01",
      "value": 0.8877
    },
    {
      "dt": "1983-10-01",
      "value": 0.9137
    },
    {
      "dt": "1983-11-01",
      "value": 0.9159
    },
    {
      "dt": "1983-12-01",
      "value": 0.9004
    },
    {
      "dt": "1984-01-01",
      "value": 0.906
    },
    {
      "dt": "1984-02-01",
      "value": 0.9348
    },
    {
      "dt": "1984-03-01",
      "value": 0.9513
    },
    {
      "dt": "1984-04-01",
      "value": 0.9231
    },
    {
      "dt": "1984-05-01",
      "value": 0.9061
    },
    {
      "dt": "1984-06-01",
      "value": 0.8826
    },
    {
      "dt": "1984-07-01",
      "value": 0.8342
    },
    {
      "dt": "1984-08-01",
      "value": 0.8473
    },
    {
      "dt": "1984-09-01",
      "value": 0.8308
    },
    {
      "dt": "1984-10-01",
      "value": 0.8364
    },
    {
      "dt": "1984-11-01",
      "value": 0.8588
    },
    {
      "dt": "1984-12-01",
      "value": 0.84
    },
    {
      "dt": "1985-01-01",
      "value": 0.8151
    },
    {
      "dt": "1985-02-01",
      "value": 0.7374
    },
    {
      "dt": "1985-03-01",
      "value": 0.697
    },
    {
      "dt": "1985-04-01",
      "value": 0.6584
    },
    {
      "dt": "1985-05-01",
      "value": 0.6768
    },
    {
      "dt": "1985-06-01",
      "value": 0.6651
    },
    {
      "dt": "1985-07-01",
      "value": 0.6995
    },
    {
      "dt": "1985-08-01",
      "value": 0.707
    },
    {
      "dt": "1985-09-01",
      "value": 0.6896
    },
    {
      "dt": "1985-10-01",
      "value": 0.7025
    },
    {
      "dt": "1985-11-01",
      "value": 0.6774
    },
    {
      "dt": "1985-12-01",
      "value": 0.6811
    },
    {
      "dt": "1986-01-01",
      "value": 0.7
    },
    {
      "dt": "1986-02-01",
      "value": 0.6993
    },
    {
      "dt": "1986-03-01",
      "value": 0.7079
    },
    {
      "dt": "1986-04-01",
      "value": 0.7228
    },
    {
      "dt": "1986-05-01",
      "value": 0.7272
    },
    {
      "dt": "1986-06-01",
      "value": 0.6889
    },
    {
      "dt": "1986-07-01",
      "value": 0.6291
    },
    {
      "dt": "1986-08-01",
      "value": 0.6123
    },
    {
      "dt": "1986-09-01",
      "value": 0.6221
    },
    {
      "dt": "1986-10-01",
      "value": 0.6383
    },
    {
      "dt": "1986-11-01",
      "value": 0.6445
    },
    {
      "dt": "1986-12-01",
      "value": 0.6595
    },
    {
      "dt": "1987-01-01",
      "value": 0.6609
    },
    {
      "dt": "1987-02-01",
      "value": 0.6677
    },
    {
      "dt": "1987-03-01",
      "value": 0.6871
    },
    {
      "dt": "1987-04-01",
      "value": 0.7114
    },
    {
      "dt": "1987-05-01",
      "value": 0.7142
    },
    {
      "dt": "1987-06-01",
      "value": 0.7179
    },
    {
      "dt": "1987-07-01",
      "value": 0.7079
    },
    {
      "dt": "1987-08-01",
      "value": 0.7072
    },
    {
      "dt": "1987-09-01",
      "value": 0.7268
    },
    {
      "dt": "1987-10-01",
      "value": 0.7112
    },
    {
      "dt": "1987-11-01",
      "value": 0.686
    },
    {
      "dt": "1987-12-01",
      "value": 0.7106
    },
    {
      "dt": "1988-01-01",
      "value": 0.7111
    },
    {
      "dt": "1988-02-01",
      "value": 0.714
    },
    {
      "dt": "1988-03-01",
      "value": 0.7329
    },
    {
      "dt": "1988-04-01",
      "value": 0.748
    },
    {
      "dt": "1988-05-01",
      "value": 0.7774
    },
    {
      "dt": "1988-06-01",
      "value": 0.8076
    },
    {
      "dt": "1988-07-01",
      "value": 0.8
    },
    {
      "dt": "1988-08-01",
      "value": 0.8057
    },
    {
      "dt": "1988-09-01",
      "value": 0.7915
    },
    {
      "dt": "1988-10-01",
      "value": 0.8096
    },
    {
      "dt": "1988-11-01",
      "value": 0.8507
    },
    {
      "dt": "1988-12-01",
      "value": 0.8573
    },
    {
      "dt": "1989-01-01",
      "value": 0.8705
    },
    {
      "dt": "1989-02-01",
      "value": 0.8564
    },
    {
      "dt": "1989-03-01",
      "value": 0.8169
    },
    {
      "dt": "1989-04-01",
      "value": 0.8035
    },
    {
      "dt": "1989-05-01",
      "value": 0.7736
    },
    {
      "dt": "1989-06-01",
      "value": 0.7561
    },
    {
      "dt": "1989-07-01",
      "value": 0.7566
    },
    {
      "dt": "1989-08-01",
      "value": 0.7635
    },
    {
      "dt": "1989-09-01",
      "value": 0.7727
    },
    {
      "dt": "1989-10-01",
      "value": 0.7742
    },
    {
      "dt": "1989-11-01",
      "value": 0.783
    },
    {
      "dt": "1989-12-01",
      "value": 0.7859
    },
    {
      "dt": "1990-01-01",
      "value": 0.7811
    },
    {
      "dt": "1990-02-01",
      "value": 0.7593
    },
    {
      "dt": "1990-03-01",
      "value": 0.7556
    },
    {
      "dt": "1990-04-01",
      "value": 0.7637
    },
    {
      "dt": "1990-05-01",
      "value": 0.7611
    },
    {
      "dt": "1990-06-01",
      "value": 0.779
    },
    {
      "dt": "1990-07-01",
      "value": 0.7908
    },
    {
      "dt": "1990-08-01",
      "value": 0.8087
    },
    {
      "dt": "1990-09-01",
      "value": 0.8251
    },
    {
      "dt": "1990-10-01",
      "value": 0.8006
    },
    {
      "dt": "1990-11-01",
      "value": 0.7729
    },
    {
      "dt": "1990-12-01",
      "value": 0.7702
    },
    {
      "dt": "1991-01-01",
      "value": 0.7793
    },
    {
      "dt": "1991-02-01",
      "value": 0.7835
    },
    {
      "dt": "1991-03-01",
      "value": 0.7711
    },
    {
      "dt": "1991-04-01",
      "value": 0.7795
    },
    {
      "dt": "1991-05-01",
      "value": 0.7743
    },
    {
      "dt": "1991-06-01",
      "value": 0.7598
    },
    {
      "dt": "1991-07-01",
      "value": 0.7716
    },
    {
      "dt": "1991-08-01",
      "value": 0.7823
    },
    {
      "dt": "1991-09-01",
      "value": 0.7937
    },
    {
      "dt": "1991-10-01",
      "value": 0.7925
    },
    {
      "dt": "1991-11-01",
      "value": 0.7866
    },
    {
      "dt": "1991-12-01",
      "value": 0.7712
    },
    {
      "dt": "1992-01-01",
      "value": 0.7476
    },
    {
      "dt": "1992-02-01",
      "value": 0.7518
    },
    {
      "dt": "1992-03-01",
      "value": 0.7586
    },
    {
      "dt": "1992-04-01",
      "value": 0.7624
    },
    {
      "dt": "1992-05-01",
      "value": 0.7559
    },
    {
      "dt": "1992-06-01",
      "value": 0.7556
    },
    {
      "dt": "1992-07-01",
      "value": 0.7451
    },
    {
      "dt": "1992-08-01",
      "value": 0.7248
    },
    {
      "dt": "1992-09-01",
      "value": 0.7225
    },
    {
      "dt": "1992-10-01",
      "value": 0.7148
    },
    {
      "dt": "1992-11-01",
      "value": 0.6898
    },
    {
      "dt": "1992-12-01",
      "value": 0.6897
    },
    {
      "dt": "1993-01-01",
      "value": 0.673
    },
    {
      "dt": "1993-02-01",
      "value": 0.6829
    },
    {
      "dt": "1993-03-01",
      "value": 0.7078
    },
    {
      "dt": "1993-04-01",
      "value": 0.7115
    },
    {
      "dt": "1993-05-01",
      "value": 0.6986
    },
    {
      "dt": "1993-06-01",
      "value": 0.6749
    },
    {
      "dt": "1993-07-01",
      "value": 0.6779
    },
    {
      "dt": "1993-08-01",
      "value": 0.6774
    },
    {
      "dt": "1993-09-01",
      "value": 0.6517
    },
    {
      "dt": "1993-10-01",
      "value": 0.661
    },
    {
      "dt": "1993-11-01",
      "value": 0.6647
    },
    {
      "dt": "1993-12-01",
      "value": 0.6736
    },
    {
      "dt": "1994-01-01",
      "value": 0.6961
    },
    {
      "dt": "1994-02-01",
      "value": 0.7161
    },
    {
      "dt": "1994-03-01",
      "value": 0.7109
    },
    {
      "dt": "1994-04-01",
      "value": 0.7156
    },
    {
      "dt": "1994-05-01",
      "value": 0.7243
    },
    {
      "dt": "1994-06-01",
      "value": 0.7329
    },
    {
      "dt": "1994-07-01",
      "value": 0.7341
    },
    {
      "dt": "1994-08-01",
      "value": 0.7401
    },
    {
      "dt": "1994-09-01",
      "value": 0.742
    },
    {
      "dt": "1994-10-01",
      "value": 0.7379
    },
    {
      "dt": "1994-11-01",
      "value": 0.7549
    },
    {
      "dt": "1994-12-01",
      "value": 0.7739
    },
    {
      "dt": "1995-01-01",
      "value": 0.7647
    },
    {
      "dt": "1995-02-01",
      "value": 0.7447
    },
    {
      "dt": "1995-03-01",
      "value": 0.7345
    },
    {
      "dt": "1995-04-01",
      "value": 0.7356
    },
    {
      "dt": "1995-05-01",
      "value": 0.7272
    },
    {
      "dt": "1995-06-01",
      "value": 0.7196
    },
    {
      "dt": "1995-07-01",
      "value": 0.7279
    },
    {
      "dt": "1995-08-01",
      "value": 0.7414
    },
    {
      "dt": "1995-09-01",
      "value": 0.7537
    },
    {
      "dt": "1995-10-01",
      "value": 0.757
    },
    {
      "dt": "1995-11-01",
      "value": 0.7453
    },
    {
      "dt": "1995-12-01",
      "value": 0.7405
    },
    {
      "dt": "1996-01-01",
      "value": 0.7417
    },
    {
      "dt": "1996-02-01",
      "value": 0.7556
    },
    {
      "dt": "1996-03-01",
      "value": 0.7714
    },
    {
      "dt": "1996-04-01",
      "value": 0.7857
    },
    {
      "dt": "1996-05-01",
      "value": 0.797
    },
    {
      "dt": "1996-06-01",
      "value": 0.7912
    },
    {
      "dt": "1996-07-01",
      "value": 0.7897
    },
    {
      "dt": "1996-08-01",
      "value": 0.783
    },
    {
      "dt": "1996-09-01",
      "value": 0.7928
    },
    {
      "dt": "1996-10-01",
      "value": 0.7918
    },
    {
      "dt": "1996-11-01",
      "value": 0.7968
    },
    {
      "dt": "1996-12-01",
      "value": 0.7966
    },
    {
      "dt": "1997-01-01",
      "value": 0.7776
    },
    {
      "dt": "1997-02-01",
      "value": 0.7677
    },
    {
      "dt": "1997-03-01",
      "value": 0.7875
    },
    {
      "dt": "1997-04-01",
      "value": 0.7787
    },
    {
      "dt": "1997-05-01",
      "value": 0.7751
    },
    {
      "dt": "1997-06-01",
      "value": 0.7542
    },
    {
      "dt": "1997-07-01",
      "value": 0.742
    },
    {
      "dt": "1997-08-01",
      "value": 0.7404
    },
    {
      "dt": "1997-09-01",
      "value": 0.7231
    },
    {
      "dt": "1997-10-01",
      "value": 0.7197
    },
    {
      "dt": "1997-11-01",
      "value": 0.6953
    },
    {
      "dt": "1997-12-01",
      "value": 0.6619
    },
    {
      "dt": "1998-01-01",
      "value": 0.6566
    },
    {
      "dt": "1998-02-01",
      "value": 0.6744
    },
    {
      "dt": "1998-03-01",
      "value": 0.6696
    },
    {
      "dt": "1998-04-01",
      "value": 0.6523
    },
    {
      "dt": "1998-05-01",
      "value": 0.6312
    },
    {
      "dt": "1998-06-01",
      "value": 0.6046
    },
    {
      "dt": "1998-07-01",
      "value": 0.618
    },
    {
      "dt": "1998-08-01",
      "value": 0.5888
    },
    {
      "dt": "1998-09-01",
      "value": 0.5889
    },
    {
      "dt": "1998-10-01",
      "value": 0.6179
    },
    {
      "dt": "1998-11-01",
      "value": 0.6349
    },
    {
      "dt": "1998-12-01",
      "value": 0.6182
    },
    {
      "dt": "1999-01-01",
      "value": 0.632
    },
    {
      "dt": "1999-02-01",
      "value": 0.6399
    },
    {
      "dt": "1999-03-01",
      "value": 0.6308
    },
    {
      "dt": "1999-04-01",
      "value": 0.642
    },
    {
      "dt": "1999-05-01",
      "value": 0.6628
    },
    {
      "dt": "1999-06-01",
      "value": 0.6563
    },
    {
      "dt": "1999-07-01",
      "value": 0.6562
    },
    {
      "dt": "1999-08-01",
      "value": 0.6446
    },
    {
      "dt": "1999-09-01",
      "value": 0.6495
    },
    {
      "dt": "1999-10-01",
      "value": 0.6509
    },
    {
      "dt": "1999-11-01",
      "value": 0.6388
    },
    {
      "dt": "1999-12-01",
      "value": 0.641
    },
    {
      "dt": "2000-01-01",
      "value": 0.656
    },
    {
      "dt": "2000-02-01",
      "value": 0.6278
    },
    {
      "dt": "2000-03-01",
      "value": 0.6094
    },
    {
      "dt": "2000-04-01",
      "value": 0.596
    },
    {
      "dt": "2000-05-01",
      "value": 0.5784
    },
    {
      "dt": "2000-06-01",
      "value": 0.5949
    },
    {
      "dt": "2000-07-01",
      "value": 0.587
    },
    {
      "dt": "2000-08-01",
      "value": 0.5808
    },
    {
      "dt": "2000-09-01",
      "value": 0.5521
    },
    {
      "dt": "2000-10-01",
      "value": 0.528
    },
    {
      "dt": "2000-11-01",
      "value": 0.5218
    },
    {
      "dt": "2000-12-01",
      "value": 0.5466
    },
    {
      "dt": "2001-01-01",
      "value": 0.5552
    },
    {
      "dt": "2001-02-01",
      "value": 0.5338
    },
    {
      "dt": "2001-03-01",
      "value": 0.5031
    },
    {
      "dt": "2001-04-01",
      "value": 0.5016
    },
    {
      "dt": "2001-05-01",
      "value": 0.5199
    },
    {
      "dt": "2001-06-01",
      "value": 0.518
    },
    {
      "dt": "2001-07-01",
      "value": 0.5089
    },
    {
      "dt": "2001-08-01",
      "value": 0.5246
    },
    {
      "dt": "2001-09-01",
      "value": 0.5036
    },
    {
      "dt": "2001-10-01",
      "value": 0.5042
    },
    {
      "dt": "2001-11-01",
      "value": 0.5165
    },
    {
      "dt": "2001-12-01",
      "value": 0.5138
    },
    {
      "dt": "2002-01-01",
      "value": 0.517
    },
    {
      "dt": "2002-02-01",
      "value": 0.5128
    },
    {
      "dt": "2002-03-01",
      "value": 0.5256
    },
    {
      "dt": "2002-04-01",
      "value": 0.5352
    },
    {
      "dt": "2002-05-01",
      "value": 0.5498
    },
    {
      "dt": "2002-06-01",
      "value": 0.5682
    },
    {
      "dt": "2002-07-01",
      "value": 0.5538
    },
    {
      "dt": "2002-08-01",
      "value": 0.5413
    },
    {
      "dt": "2002-09-01",
      "value": 0.5465
    },
    {
      "dt": "2002-10-01",
      "value": 0.5502
    },
    {
      "dt": "2002-11-01",
      "value": 0.5613
    },
    {
      "dt": "2002-12-01",
      "value": 0.5624
    },
    {
      "dt": "2003-01-01",
      "value": 0.5829
    },
    {
      "dt": "2003-02-01",
      "value": 0.5956
    },
    {
      "dt": "2003-03-01",
      "value": 0.6015
    },
    {
      "dt": "2003-04-01",
      "value": 0.61
    },
    {
      "dt": "2003-05-01",
      "value": 0.6468
    },
    {
      "dt": "2003-06-01",
      "value": 0.6652
    },
    {
      "dt": "2003-07-01",
      "value": 0.6607
    },
    {
      "dt": "2003-08-01",
      "value": 0.6518
    },
    {
      "dt": "2003-09-01",
      "value": 0.6635
    },
    {
      "dt": "2003-10-01",
      "value": 0.6948
    },
    {
      "dt": "2003-11-01",
      "value": 0.7158
    },
    {
      "dt": "2003-12-01",
      "value": 0.7391
    },
    {
      "dt": "2004-01-01",
      "value": 0.7717
    },
    {
      "dt": "2004-02-01",
      "value": 0.777
    },
    {
      "dt": "2004-03-01",
      "value": 0.7496
    },
    {
      "dt": "2004-04-01",
      "value": 0.7443
    },
    {
      "dt": "2004-05-01",
      "value": 0.7039
    },
    {
      "dt": "2004-06-01",
      "value": 0.6937
    },
    {
      "dt": "2004-07-01",
      "value": 0.7161
    },
    {
      "dt": "2004-08-01",
      "value": 0.7111
    },
    {
      "dt": "2004-09-01",
      "value": 0.7028
    },
    {
      "dt": "2004-10-01",
      "value": 0.7337
    },
    {
      "dt": "2004-11-01",
      "value": 0.7704
    },
    {
      "dt": "2004-12-01",
      "value": 0.7675
    },
    {
      "dt": "2005-01-01",
      "value": 0.7668
    },
    {
      "dt": "2005-02-01",
      "value": 0.7812
    },
    {
      "dt": "2005-03-01",
      "value": 0.7848
    },
    {
      "dt": "2005-04-01",
      "value": 0.7738
    },
    {
      "dt": "2005-05-01",
      "value": 0.7663
    },
    {
      "dt": "2005-06-01",
      "value": 0.7667
    },
    {
      "dt": "2005-07-01",
      "value": 0.7524
    },
    {
      "dt": "2005-08-01",
      "value": 0.7614
    },
    {
      "dt": "2005-09-01",
      "value": 0.7651
    },
    {
      "dt": "2005-10-01",
      "value": 0.7535
    },
    {
      "dt": "2005-11-01",
      "value": 0.7353
    },
    {
      "dt": "2005-12-01",
      "value": 0.7423
    },
    {
      "dt": "2006-01-01",
      "value": 0.7505
    },
    {
      "dt": "2006-02-01",
      "value": 0.7418
    },
    {
      "dt": "2006-03-01",
      "value": 0.7266
    },
    {
      "dt": "2006-04-01",
      "value": 0.7369
    },
    {
      "dt": "2006-05-01",
      "value": 0.7639
    },
    {
      "dt": "2006-06-01",
      "value": 0.7399
    },
    {
      "dt": "2006-07-01",
      "value": 0.7528
    },
    {
      "dt": "2006-08-01",
      "value": 0.7631
    },
    {
      "dt": "2006-09-01",
      "value": 0.7549
    },
    {
      "dt": "2006-10-01",
      "value": 0.7544
    },
    {
      "dt": "2006-11-01",
      "value": 0.7728
    },
    {
      "dt": "2006-12-01",
      "value": 0.7858
    },
    {
      "dt": "2007-01-01",
      "value": 0.7826
    },
    {
      "dt": "2007-02-01",
      "value": 0.783
    },
    {
      "dt": "2007-03-01",
      "value": 0.7932
    },
    {
      "dt": "2007-04-01",
      "value": 0.8273
    },
    {
      "dt": "2007-05-01",
      "value": 0.8254
    },
    {
      "dt": "2007-06-01",
      "value": 0.8423
    },
    {
      "dt": "2007-07-01",
      "value": 0.8677
    },
    {
      "dt": "2007-08-01",
      "value": 0.8291
    },
    {
      "dt": "2007-09-01",
      "value": 0.8461
    },
    {
      "dt": "2007-10-01",
      "value": 0.8996
    },
    {
      "dt": "2007-11-01",
      "value": 0.8961
    },
    {
      "dt": "2007-12-01",
      "value": 0.8719
    },
    {
      "dt": "2008-01-01",
      "value": 0.8823
    },
    {
      "dt": "2008-02-01",
      "value": 0.9133
    },
    {
      "dt": "2008-03-01",
      "value": 0.9221
    },
    {
      "dt": "2008-04-01",
      "value": 0.9309
    },
    {
      "dt": "2008-05-01",
      "value": 0.9492
    },
    {
      "dt": "2008-06-01",
      "value": 0.9511
    },
    {
      "dt": "2008-07-01",
      "value": 0.962
    },
    {
      "dt": "2008-08-01",
      "value": 0.8815
    },
    {
      "dt": "2008-09-01",
      "value": 0.8168
    },
    {
      "dt": "2008-10-01",
      "value": 0.687
    },
    {
      "dt": "2008-11-01",
      "value": 0.6591
    },
    {
      "dt": "2008-12-01",
      "value": 0.6719
    },
    {
      "dt": "2009-01-01",
      "value": 0.6754
    },
    {
      "dt": "2009-02-01",
      "value": 0.6504
    },
    {
      "dt": "2009-03-01",
      "value": 0.6666
    },
    {
      "dt": "2009-04-01",
      "value": 0.7158
    },
    {
      "dt": "2009-05-01",
      "value": 0.7648
    },
    {
      "dt": "2009-06-01",
      "value": 0.8025
    },
    {
      "dt": "2009-07-01",
      "value": 0.8049
    },
    {
      "dt": "2009-08-01",
      "value": 0.8353
    },
    {
      "dt": "2009-09-01",
      "value": 0.8622
    },
    {
      "dt": "2009-10-01",
      "value": 0.9067
    },
    {
      "dt": "2009-11-01",
      "value": 0.9197
    },
    {
      "dt": "2009-12-01",
      "value": 0.9021
    },
    {
      "dt": "2010-01-01",
      "value": 0.9127
    },
    {
      "dt": "2010-02-01",
      "value": 0.8857
    },
    {
      "dt": "2010-03-01",
      "value": 0.9123
    },
    {
      "dt": "2010-04-01",
      "value": 0.9262
    },
    {
      "dt": "2010-05-01",
      "value": 0.8713
    },
    {
      "dt": "2010-06-01",
      "value": 0.8539
    },
    {
      "dt": "2010-07-01",
      "value": 0.8786
    },
    {
      "dt": "2010-08-01",
      "value": 0.9004
    },
    {
      "dt": "2010-09-01",
      "value": 0.9398
    },
    {
      "dt": "2010-10-01",
      "value": 0.9818
    },
    {
      "dt": "2010-11-01",
      "value": 0.9889
    },
    {
      "dt": "2010-12-01",
      "value": 0.9929
    },
    {
      "dt": "2011-01-01",
      "value": 0.9962
    },
    {
      "dt": "2011-02-01",
      "value": 1.0084
    },
    {
      "dt": "2011-03-01",
      "value": 1.0113
    },
    {
      "dt": "2011-04-01",
      "value": 1.0588
    },
    {
      "dt": "2011-05-01",
      "value": 1.0675
    },
    {
      "dt": "2011-06-01",
      "value": 1.0617
    },
    {
      "dt": "2011-07-01",
      "value": 1.0781
    },
    {
      "dt": "2011-08-01",
      "value": 1.0502
    },
    {
      "dt": "2011-09-01",
      "value": 1.022
    },
    {
      "dt": "2011-10-01",
      "value": 1.0168
    },
    {
      "dt": "2011-11-01",
      "value": 1.0112
    },
    {
      "dt": "2011-12-01",
      "value": 1.0122
    },
    {
      "dt": "2012-01-01",
      "value": 1.0415
    },
    {
      "dt": "2012-02-01",
      "value": 1.0732
    },
    {
      "dt": "2012-03-01",
      "value": 1.0526
    },
    {
      "dt": "2012-04-01",
      "value": 1.035
    },
    {
      "dt": "2012-05-01",
      "value": 0.998
    },
    {
      "dt": "2012-06-01",
      "value": 0.9986
    },
    {
      "dt": "2012-07-01",
      "value": 1.03
    },
    {
      "dt": "2012-08-01",
      "value": 1.0475
    },
    {
      "dt": "2012-09-01",
      "value": 1.0406
    },
    {
      "dt": "2012-10-01",
      "value": 1.0298
    },
    {
      "dt": "2012-11-01",
      "value": 1.0405
    },
    {
      "dt": "2012-12-01",
      "value": 1.0465
    },
    {
      "dt": "2013-01-01",
      "value": 1.05
    },
    {
      "dt": "2013-02-01",
      "value": 1.031
    },
    {
      "dt": "2013-03-01",
      "value": 1.0345
    },
    {
      "dt": "2013-04-01",
      "value": 1.038
    },
    {
      "dt": "2013-05-01",
      "value": 0.9919
    },
    {
      "dt": "2013-06-01",
      "value": 0.944
    },
    {
      "dt": "2013-07-01",
      "value": 0.9155
    },
    {
      "dt": "2013-08-01",
      "value": 0.9037
    },
    {
      "dt": "2013-09-01",
      "value": 0.9303
    },
    {
      "dt": "2013-10-01",
      "value": 0.9519
    },
    {
      "dt": "2013-11-01",
      "value": 0.9324
    },
    {
      "dt": "2013-12-01",
      "value": 0.898
    },
    {
      "dt": "2014-01-01",
      "value": 0.8858
    },
    {
      "dt": "2014-02-01",
      "value": 0.8974
    },
    {
      "dt": "2014-03-01",
      "value": 0.9089
    },
    {
      "dt": "2014-04-01",
      "value": 0.9315
    },
    {
      "dt": "2014-05-01",
      "value": 0.9305
    },
    {
      "dt": "2014-06-01",
      "value": 0.9365
    },
    {
      "dt": "2014-07-01",
      "value": 0.9389
    },
    {
      "dt": "2014-08-01",
      "value": 0.9309
    },
    {
      "dt": "2014-09-01",
      "value": 0.9042
    },
    {
      "dt": "2014-10-01",
      "value": 0.8781
    },
    {
      "dt": "2014-11-01",
      "value": 0.8644
    },
    {
      "dt": "2014-12-01",
      "value": 0.8257
    },
    {
      "dt": "2015-01-01",
      "value": 0.8064
    },
    {
      "dt": "2015-02-01",
      "value": 0.7797
    },
    {
      "dt": "2015-03-01",
      "value": 0.7724
    },
    {
      "dt": "2015-04-01",
      "value": 0.774
    },
    {
      "dt": "2015-05-01",
      "value": 0.7891
    },
    {
      "dt": "2015-06-01",
      "value": 0.7715
    },
    {
      "dt": "2015-07-01",
      "value": 0.7407
    },
    {
      "dt": "2015-08-01",
      "value": 0.7295
    },
    {
      "dt": "2015-09-01",
      "value": 0.7059
    },
    {
      "dt": "2015-10-01",
      "value": 0.72
    },
    {
      "dt": "2015-11-01",
      "value": 0.7146
    },
    {
      "dt": "2015-12-01",
      "value": 0.7247
    },
    {
      "dt": "2016-01-01",
      "value": 0.7011
    },
    {
      "dt": "2016-02-01",
      "value": 0.7134
    },
    {
      "dt": "2016-03-01",
      "value": 0.7504
    },
    {
      "dt": "2016-04-01",
      "value": 0.7664
    },
    {
      "dt": "2016-05-01",
      "value": 0.7318
    },
    {
      "dt": "2016-06-01",
      "value": 0.7401
    },
    {
      "dt": "2016-07-01",
      "value": 0.7529
    },
    {
      "dt": "2016-08-01",
      "value": 0.7629
    },
    {
      "dt": "2016-09-01",
      "value": 0.7591
    },
    {
      "dt": "2016-10-01",
      "value": 0.7615
    },
    {
      "dt": "2016-11-01",
      "value": 0.7532
    },
    {
      "dt": "2016-12-01",
      "value": 0.7346
    },
    {
      "dt": "2017-01-01",
      "value": 0.7465
    },
    {
      "dt": "2017-02-01",
      "value": 0.7664
    },
    {
      "dt": "2017-03-01",
      "value": 0.7622
    },
    {
      "dt": "2017-04-01",
      "value": 0.7534
    },
    {
      "dt": "2017-05-01",
      "value": 0.7437
    },
    {
      "dt": "2017-06-01",
      "value": 0.7562
    },
    {
      "dt": "2017-07-01",
      "value": 0.7807
    },
    {
      "dt": "2017-08-01",
      "value": 0.7915
    },
    {
      "dt": "2017-09-01",
      "value": 0.7974
    },
    {
      "dt": "2017-10-01",
      "value": 0.7788
    },
    {
      "dt": "2017-11-01",
      "value": 0.762
    },
    {
      "dt": "2017-12-01",
      "value": 0.7648
    },
    {
      "dt": "2018-01-01",
      "value": 0.7956
    },
    {
      "dt": "2018-02-01",
      "value": 0.7867
    },
    {
      "dt": "2018-03-01",
      "value": 0.7759
    },
    {
      "dt": "2018-04-01",
      "value": 0.7684
    },
    {
      "dt": "2018-05-01",
      "value": 0.7525
    },
    {
      "dt": "2018-06-01",
      "value": 0.7498
    },
    {
      "dt": "2018-07-01",
      "value": 0.7403
    },
    {
      "dt": "2018-08-01",
      "value": 0.7325
    },
    {
      "dt": "2018-09-01",
      "value": 0.7206
    },
    {
      "dt": "2018-10-01",
      "value": 0.7111
    },
    {
      "dt": "2018-11-01",
      "value": 0.7247
    },
    {
      "dt": "2018-12-01",
      "value": 0.7169
    },
    {
      "dt": "2019-01-01",
      "value": 0.7151
    },
    {
      "dt": "2019-02-01",
      "value": 0.7136
    },
    {
      "dt": "2019-03-01",
      "value": 0.7082
    },
    {
      "dt": "2019-04-01",
      "value": 0.7111
    },
    {
      "dt": "2019-05-01",
      "value": 0.6945
    },
    {
      "dt": "2019-06-01",
      "value": 0.6946
    },
    {
      "dt": "2019-07-01",
      "value": 0.6978
    },
    {
      "dt": "2019-08-01",
      "value": 0.6775
    },
    {
      "dt": "2019-09-01",
      "value": 0.6815
    },
    {
      "dt": "2019-10-01",
      "value": 0.6798
    },
    {
      "dt": "2019-11-01",
      "value": 0.6827
    },
    {
      "dt": "2019-12-01",
      "value": 0.6887
    },
    {
      "dt": "2020-01-01",
      "value": 0.6851
    },
    {
      "dt": "2020-02-01",
      "value": 0.6664
    },
    {
      "dt": "2020-03-01",
      "value": 0.6218
    },
    {
      "dt": "2020-04-01",
      "value": 0.6312
    },
    {
      "dt": "2020-05-01",
      "value": 0.6517
    },
    {
      "dt": "2020-06-01",
      "value": 0.6899
    },
    {
      "dt": "2020-07-01",
      "value": 0.704
    },
    {
      "dt": "2020-08-01",
      "value": 0.7203
    },
    {
      "dt": "2020-09-01",
      "value": 0.7224
    },
    {
      "dt": "2020-10-01",
      "value": 0.7121
    },
    {
      "dt": "2020-11-01",
      "value": 0.727
    },
    {
      "dt": "2020-12-01",
      "value": 0.7532
    },
    {
      "dt": "2021-01-01",
      "value": 0.7726
    },
    {
      "dt": "2021-02-01",
      "value": 0.7753
    },
    {
      "dt": "2021-03-01",
      "value": 0.771
    },
    {
      "dt": "2021-04-01",
      "value": 0.7701
    },
    {
      "dt": "2021-05-01",
      "value": 0.7763
    },
    {
      "dt": "2021-06-01",
      "value": 0.7643
    },
    {
      "dt": "2021-07-01",
      "value": 0.7417
    },
    {
      "dt": "2021-08-01",
      "value": 0.7304
    },
    {
      "dt": "2021-09-01",
      "value": 0.7312
    },
    {
      "dt": "2021-10-01",
      "value": 0.7412
    },
    {
      "dt": "2021-11-01",
      "value": 0.7307
    },
    {
      "dt": "2021-12-01",
      "value": 0.7155
    },
    {
      "dt": "2022-01-01",
      "value": 0.718
    },
    {
      "dt": "2022-02-01",
      "value": 0.7169
    },
    {
      "dt": "2022-03-01",
      "value": 0.7374
    },
    {
      "dt": "2022-04-01",
      "value": 0.7364
    },
    {
      "dt": "2022-05-01",
      "value": 0.7041
    },
    {
      "dt": "2022-06-01",
      "value": 0.7025
    },
    {
      "dt": "2022-07-01",
      "value": 0.6856
    },
    {
      "dt": "2022-08-01",
      "value": 0.6961
    },
    {
      "dt": "2022-09-01",
      "value": 0.6671
    },
    {
      "dt": "2022-10-01",
      "value": 0.637
    },
    {
      "dt": "2022-11-01",
      "value": 0.6596
    },
    {
      "dt": "2022-12-01",
      "value": 0.6748
    },
    {
      "dt": "2023-01-01",
      "value": 0.6955
    },
    {
      "dt": "2023-02-01",
      "value": 0.6893
    },
    {
      "dt": "2023-03-01",
      "value": 0.6676
    },
    {
      "dt": "2023-04-01",
      "value": 0.6688
    },
    {
      "dt": "2023-05-01",
      "value": 0.6643
    },
    {
      "dt": "2023-06-01",
      "value": 0.6713
    },
    {
      "dt": "2023-07-01",
      "value": 0.6742
    },
    {
      "dt": "2023-08-01",
      "value": 0.6486
    },
    {
      "dt": "2023-09-01",
      "value": 0.6425
    },
    {
      "dt": "2023-10-01",
      "value": 0.6347
    },
    {
      "dt": "2023-11-01",
      "value": 0.6508
    },
    {
      "dt": "2023-12-01",
      "value": 0.6693
    },
    {
      "dt": "2024-01-01",
      "value": 0.6636
    },
    {
      "dt": "2024-02-01",
      "value": 0.6522
    },
    {
      "dt": "2024-03-01",
      "value": 0.6558
    },
    {
      "dt": "2024-04-01",
      "value": 0.6507
    },
    {
      "dt": "2024-05-01",
      "value": 0.6626
    },
    {
      "dt": "2024-06-01",
      "value": 0.6642
    },
    {
      "dt": "2024-07-01",
      "value": 0.6673
    },
    {
      "dt": "2024-08-01",
      "value": 0.6658
    },
    {
      "dt": "2024-09-01",
      "value": 0.677
    },
    {
      "dt": "2024-10-01",
      "value": 0.67
    },
    {
      "dt": "2024-11-01",
      "value": 0.6528
    },
    {
      "dt": "2024-12-01",
      "value": 0.6334
    },
    {
      "dt": "2025-01-01",
      "value": 0.6231
    },
    {
      "dt": "2025-02-01",
      "value": 0.6301
    },
    {
      "dt": "2025-03-01",
      "value": 0.63
    },
    {
      "dt": "2025-04-01",
      "value": 0.6291
    },
    {
      "dt": "2025-05-01",
      "value": 0.6435
    },
    {
      "dt": "2025-06-01",
      "value": 0.6509
    },
    {
      "dt": "2025-07-01",
      "value": 0.6536
    },
    {
      "dt": "2025-08-01",
      "value": 0.6495
    },
    {
      "dt": "2025-09-01",
      "value": 0.6598
    },
    {
      "dt": "2025-10-01",
      "value": 0.6547
    },
    {
      "dt": "2025-11-01",
      "value": 0.6502
    },
    {
      "dt": "2025-12-01",
      "value": 0.6643
    },
    {
      "dt": "2026-01-01",
      "value": 0.6792
    },
    {
      "dt": "2026-02-01",
      "value": 0.706
    },
    {
      "dt": "2026-03-01",
      "value": 0.7017
    }
  ],
  "bands": [
    {
      "from": "1854-12-01",
      "to": "1854-12-01",
      "color": "rgba(148, 163, 184, .16)"
    },
    {
      "from": "1857-07-01",
      "to": "1858-12-01",
      "color": "rgba(148, 163, 184, .16)"
    },
    {
      "from": "1860-11-01",
      "to": "1861-06-01",
      "color": "rgba(148, 163, 184, .16)"
    },
    {
      "from": "1865-05-01",
      "to": "1867-12-01",
      "color": "rgba(148, 163, 184, .16)"
    },
    {
      "from": "1869-07-01",
      "to": "1870-12-01",
      "color": "rgba(148, 163, 184, .16)"
    },
    {
      "from": "1873-11-01",
      "to": "1879-03-01",
      "color": "rgba(148, 163, 184, .16)"
    },
    {
      "from": "1882-04-01",
      "to": "1885-05-01",
      "color": "rgba(148, 163, 184, .16)"
    },
    {
      "from": "1887-04-01",
      "to": "1888-04-01",
      "color": "rgba(148, 163, 184, .16)"
    },
    {
      "from": "1890-08-01",
      "to": "1891-05-01",
      "color": "rgba(148, 163, 184, .16)"
    },
    {
      "from": "1893-02-01",
      "to": "1894-06-01",
      "color": "rgba(148, 163, 184, .16)"
    },
    {
      "from": "1896-01-01",
      "to": "1897-06-01",
      "color": "rgba(148, 163, 184, .16)"
    },
    {
      "from": "1899-07-01",
      "to": "1900-12-01",
      "color": "rgba(148, 163, 184, .16)"
    },
    {
      "from": "1902-10-01",
      "to": "1904-08-01",
      "color": "rgba(148, 163, 184, .16)"
    },
    {
      "from": "1907-06-01",
      "to": "1908-06-01",
      "color": "rgba(148, 163, 184, .16)"
    },
    {
      "from": "1910-02-01",
      "to": "1912-01-01",
      "color": "rgba(148, 163, 184, .16)"
    },
    {
      "from": "1913-02-01",
      "to": "1914-12-01",
      "color": "rgba(148, 163, 184, .16)"
    },
    {
      "from": "1918-09-01",
      "to": "1919-03-01",
      "color": "rgba(148, 163, 184, .16)"
    },
    {
      "from": "1920-02-01",
      "to": "1921-07-01",
      "color": "rgba(148, 163, 184, .16)"
    },
    {
      "from": "1923-06-01",
      "to": "1924-07-01",
      "color": "rgba(148, 163, 184, .16)"
    },
    {
      "from": "1926-11-01",
      "to": "1927-11-01",
      "color": "rgba(148, 163, 184, .16)"
    },
    {
      "from": "1929-09-01",
      "to": "1933-03-01",
      "color": "rgba(148, 163, 184, .16)"
    },
    {
      "from": "1937-06-01",
      "to": "1938-06-01",
      "color": "rgba(148, 163, 184, .16)"
    },
    {
      "from": "1945-03-01",
      "to": "1945-10-01",
      "color": "rgba(148, 163, 184, .16)"
    },
    {
      "from": "1948-12-01",
      "to": "1949-10-01",
      "color": "rgba(148, 163, 184, .16)"
    },
    {
      "from": "1953-08-01",
      "to": "1954-05-01",
      "color": "rgba(148, 163, 184, .16)"
    },
    {
      "from": "1957-09-01",
      "to": "1958-04-01",
      "color": "rgba(148, 163, 184, .16)"
    },
    {
      "from": "1960-05-01",
      "to": "1961-02-01",
      "color": "rgba(148, 163, 184, .16)"
    },
    {
      "from": "1970-01-01",
      "to": "1970-11-01",
      "color": "rgba(148, 163, 184, .16)"
    },
    {
      "from": "1973-12-01",
      "to": "1975-03-01",
      "color": "rgba(148, 163, 184, .16)"
    },
    {
      "from": "1980-02-01",
      "to": "1980-07-01",
      "color": "rgba(148, 163, 184, .16)"
    },
    {
      "from": "1981-08-01",
      "to": "1982-11-01",
      "color": "rgba(148, 163, 184, .16)"
    },
    {
      "from": "1990-08-01",
      "to": "1991-03-01",
      "color": "rgba(148, 163, 184, .16)"
    },
    {
      "from": "2001-04-01",
      "to": "2001-11-01",
      "color": "rgba(148, 163, 184, .16)"
    },
    {
      "from": "2008-01-01",
      "to": "2009-06-01",
      "color": "rgba(148, 163, 184, .16)"
    },
    {
      "from": "2020-03-01",
      "to": "2020-04-01",
      "color": "rgba(148, 163, 184, .16)"
    }
  ]
}